{
    "members": [
        {
            "name": "Son Son Asian Eats",
            "membershipLevel": 3,
            "category": "Food & Beverage",
            "address": "360 W 2650 N #3 Pleasant View, UT 84414",
            "phone": "801-710-2448",
            "website": "https://sonsoneats.com/",
            "logo": "images/sonson.webp"
        },
        {
            "name": "Anytime Fitness",
            "membershipLevel": 2,
            "category": "Health & Wellness",
            "address": "455 N Washington Blvd Suite 432, Harrisville, UT 84404",
            "phone": "385-600-7060",
            "website": "https://www.anytimefitness.com/locations/harrisville-utah-5306",
            "logo": "images/anytime-fitness.webp"
        },
        {
            "name": "Key Choice Realty LLC",
            "membershipLevel": 1,
            "category": "Real Estate",
            "address": "4130 Alder Creek Dr, Pleasant View, UT 84414",
            "phone": "801-391-5550",
            "website": "https://www.keychoicerealty.com/",
            "logo": "images/key-choice.webp"
        },
        {
            "name": "Proponent IT",
            "membershipLevel": 2,
            "category": "Information Technology",
            "address": "3055 W 2600 N St, Ogden, UT 84404",
            "phone": "801-621-2999",
            "website": "https://proponentit.com/",
            "logo": "images/proponant.webp"
        },
        {
            "name": "Bank of Utah",
            "membershipLevel": 3,
            "category": "Financial Services",
            "address": "115 Washington Blvd, Ogden, UT 84404",
            "phone": "801-399-4425",
            "website": "https://www.bankofutah.com/locations/ben-lomond",
            "logo": "images/Bank_of_Utah.webp"
        },
        {
            "name": "Smith & Edwards",
            "membershipLevel": 1,
            "category": "Retail",
            "address": "3936 N 2000 W, Ogden, UT 84404",
            "phone": "801-731-1120",
            "website": "https://www.smithandedwards.com/",
            "logo": "images/smith-edwards.webp"
        },
        {
            "name": "Mountain View Dental Care",
            "membershipLevel": 2,
            "category": "Healthcare",
            "address": "539 Harrisville Rd F, Harrisville, UT 84404",
            "phone": "801-786-0700",
            "website": "https://www.mountainvistadentalcare.com/",
            "logo": "images/mountain-view-dental.webp"
        }
    ]
}